z3c/jbot/README.rst
z3c/jbot/__init__.py
z3c/jbot/browser.py
z3c/jbot/configure.zcml
z3c/jbot/interfaces.py
z3c/jbot/manager.py
z3c/jbot/meta.zcml
z3c/jbot/metaconfigure.py
z3c/jbot/metadirectives.py
z3c/jbot/patches.py
z3c/jbot/utility.py
z3c/jbot/tests/__init__.py
z3c/jbot/tests/common.py
z3c/jbot/tests/test_doctests.py
z3c/jbot/tests/test_five.py
z3c/jbot/tests/overrides/http/z3c.jbot.tests.templates.example.pt
z3c/jbot/tests/overrides/https/z3c.jbot.tests.templates.example.pt
z3c/jbot/tests/overrides/interface/z3c.jbot.tests.templates.example.pt
z3c/jbot/tests/overrides/interface_deprecated/z3c.jbot.tests.templates.example_deprecated.pt
z3c/jbot/tests/overrides/request/z3c.jbot.tests.templates.example.pt
z3c/jbot/tests/overrides/resources/z3c.jbot.tests.resources.test.txt
z3c/jbot/tests/resources/test.txt
z3c/jbot/tests/templates/example.pt
z3c_jbot-3.1.dist-info/LICENSE.rst
z3c_jbot-3.1.dist-info/METADATA
z3c_jbot-3.1.dist-info/WHEEL
z3c_jbot-3.1.dist-info/entry_points.txt
z3c_jbot-3.1.dist-info/top_level.txt
z3c_jbot-3.1.dist-info/RECORD
