Metadata-Version: 2.2
Name: z3c.jbot
Version: 3.1
Summary: Drop-in template overrides.
Home-page: https://github.com/zopefoundation/z3c.jbot
Author: Zope Foundation and Contributors
Author-email: zope-dev@zope.dev
License: ZPL-2.1
Keywords: page template override
Classifier: Development Status :: 5 - Production/Stable
Classifier: Framework :: Zope
Classifier: Framework :: Zope :: 3
Classifier: Framework :: Zope :: 5
Classifier: License :: OSI Approved :: Zope Public License
Classifier: Programming Language :: Python
Classifier: Programming Language :: Python :: 3.9
Classifier: Programming Language :: Python :: 3.10
Classifier: Programming Language :: Python :: 3.11
Classifier: Programming Language :: Python :: 3.12
Classifier: Programming Language :: Python :: 3.13
Requires-Python: >=3.9
License-File: LICENSE.rst
Requires-Dist: setuptools
Requires-Dist: zope.pagetemplate
Requires-Dist: zope.component
Requires-Dist: zope.configuration
Requires-Dist: zope.security
Requires-Dist: zope.publisher
Provides-Extra: test
Requires-Dist: Zope; extra == "test"
Requires-Dist: Products.BTreeFolder2; extra == "test"
Requires-Dist: Products.CMFCore; extra == "test"
Requires-Dist: plone.resource; extra == "test"
Dynamic: author
Dynamic: author-email
Dynamic: classifier
Dynamic: description
Dynamic: description-content-type
Dynamic: home-page
Dynamic: keywords
Dynamic: license
Dynamic: provides-extra
Dynamic: requires-dist
Dynamic: requires-python
Dynamic: summary
